[
  {
    "location": {
      "url": "/a/",
      "method": "get",
      "node": {
        "name": "Query",
        "child": {
          "name": "limit"
        }
      }
    },
    "code": "DeletedRequiredParam",
    "compatibility": "Breaking"
  },
  {
    "location": {
      "url": "/a/{id}",
      "method": "get",
      "node": {
        "name": "Path",
        "child": {
          "name": "id"
        }
      }
    },
    "code": "NarrowedType",
    "compatibility": "Breaking",
    "info": "string -> integer"
  }
]